README.rst
setup.cfg
setup.py
drf_generators/__init__.py
drf_generators/generators.py
drf_generators.egg-info/PKG-INFO
drf_generators.egg-info/SOURCES.txt
drf_generators.egg-info/dependency_links.txt
drf_generators.egg-info/requires.txt
drf_generators.egg-info/top_level.txt
drf_generators/management/commands/__init__.py
drf_generators/management/commands/generate.py
drf_generators/templates/__init__.py
drf_generators/templates/apiview.py
drf_generators/templates/function.py
drf_generators/templates/modelviewset.py
drf_generators/templates/serializer.py
drf_generators/templates/viewset.py