Metadata-Version: 1.1
Name: drf-generators
Version: 0.2.5
Summary: Generate DRF Serializers, Views, and urls for your API aplication.
Home-page: https://github.com/brobin/drf-generators
Author: Tobin Brown
Author-email: tobin@brobin.me
License: MIT
Download-URL: https://github.com/brobin/drf-generators/archive/0.2.5.zip
Keywords: API REST framework generate
Platform: UNKNOWN
Classifier: Environment :: Web Environment
Classifier: Framework :: Django :: 1.7
Classifier: Framework :: Django :: 1.8
Classifier: Intended Audience :: Developers
Classifier: License :: OSI Approved :: MIT License
Classifier: Operating System :: OS Independent
Classifier: Natural Language :: English
Classifier: Programming Language :: Python :: 2.7
Classifier: Programming Language :: Python :: 3.2
Classifier: Programming Language :: Python :: 3.3
Classifier: Programming Language :: Python :: 3.4
Classifier: Topic :: Internet :: WWW/HTTP
